{
  "name": "Pamuk",
  "species": "Tavşan",
  "emoji": "🐰",
  "display_size": 180,
  "idle_frame": "idle_open.png",
  "sleep_frame": "sleeping.png",
  "float": {
    "amplitude_px": 3,
    "period_ms": 2400
  },
  "sleep": {
    "enabled": true,
    "idle_timeout_ms": 15000,
    "float_amplitude_px": 2,
    "float_period_ms": 4500
  },
  "walk": {
    "enabled": true,
    "walk_probability": 0.5,
    "min_distance_px": 60,
    "max_distance_px": 220,
    "hop_distance_px": 50,
    "hop_duration_ms": 500,
    "hop_height_px": 35,
    "hop_pause_ms": 280,
    "frames": ["walk_1.png", "walk_2.png"]
  },
  "idle_event": {
    "min_interval_ms": 2000,
    "max_interval_ms": 5000
  },
  "bubbles": {
    "random_emojis": ["🥕", "✨", "🌸", "🌿"],
    "min_interval_ms": 10000,
    "max_interval_ms": 25000,
    "duration_ms": 2500
  },
  "behaviors": {
    "blink": {
      "frames": ["idle_open.png", "idle_half.png", "idle_closed.png", "idle_half.png", "idle_open.png"],
      "frame_duration_ms": 90,
      "weight": 6,
      "min_interval_ms": 3000,
      "max_interval_ms": 7000
    },
    "ear_wiggle": {
      "frames": ["idle_open.png", "ear_tilt.png", "idle_open.png", "ear_tilt.png", "idle_open.png"],
      "frame_duration_ms": 140,
      "weight": 3,
      "min_interval_ms": 8000,
      "max_interval_ms": 20000
    },
    "yawn": {
      "frames": ["idle_open.png", "idle_half.png", "yawn.png", "yawn.png", "yawn.png", "idle_half.png", "idle_open.png"],
      "frame_duration_ms": 200,
      "weight": 1,
      "min_interval_ms": 25000,
      "max_interval_ms": 60000
    },
    "look_around": {
      "frames": ["idle_open.png", "look_right.png", "look_right.png", "look_right.png", "idle_open.png"],
      "frame_duration_ms": 280,
      "weight": 2,
      "min_interval_ms": 10000,
      "max_interval_ms": 25000
    }
  }
}